elasticsearch2_backend.py
elasticsearch2_haystack-0.1.dist-info/DESCRIPTION.rst
elasticsearch2_haystack-0.1.dist-info/METADATA
elasticsearch2_haystack-0.1.dist-info/RECORD
elasticsearch2_haystack-0.1.dist-info/WHEEL
elasticsearch2_haystack-0.1.dist-info/metadata.json
elasticsearch2_haystack-0.1.dist-info/top_level.txt
