Metadata-Version: 2.0
Name: elasticsearch2-haystack
Version: 0.1
Summary: An elasticsearch2 compatible backend for Haystack
Home-page: http://github.com/ndevox/elasticsearch2-haystack
Author: Nick Sarbicki
Author-email: nick.a.sarbicki@gmail.com
License: GPL2
Download-URL: http://github.com/ndevox/elasticsearch2-haystack/tarball/V0.1
Platform: UNKNOWN
Classifier: Development Status :: 5 - Production/Stable
Classifier: Intended Audience :: Developers
Classifier: License :: OSI Approved :: GNU General Public License (GPL)
Classifier: Topic :: Internet :: WWW/HTTP :: Indexing/Search
Classifier: Framework :: Django
Requires-Dist: django-haystack (>=2)
Requires-Dist: elasticsearch (<5)
